[{"tags":{},"filePath":"/packages/components/src/layout/src/Flex.tsx","description":"The Flex component is used to create a flex container and provides some shortcuts for the flex properties.\n\n[View Documentation](TODO)","displayName":"Flex","methods":[],"props":{"style":{"defaultValue":null,"description":"","name":"style","parent":{"fileName":"wl-hopper/node_modules/.pnpm/@types+react@18.3.3/node_modules/@types/react/index.d.ts","name":"HTMLAttributes"},"declarations":[{"fileName":"wl-hopper/node_modules/.pnpm/@types+react@18.3.3/node_modules/@types/react/index.d.ts","name":"HTMLAttributes"}],"required":false,"type":{"name":"CSSProperties"}},"className":{"defaultValue":null,"description":"","name":"className","parent":{"fileName":"wl-hopper/node_modules/.pnpm/@types+react@18.3.3/node_modules/@types/react/index.d.ts","name":"HTMLAttributes"},"declarations":[{"fileName":"wl-hopper/node_modules/.pnpm/@types+react@18.3.3/node_modules/@types/react/index.d.ts","name":"HTMLAttributes"}],"required":false,"type":{"name":"string"}},"id":{"defaultValue":null,"description":"","name":"id","parent":{"fileName":"wl-hopper/node_modules/.pnpm/@types+react@18.3.3/node_modules/@types/react/index.d.ts","name":"HTMLAttributes"},"declarations":[{"fileName":"wl-hopper/node_modules/.pnpm/@types+react@18.3.3/node_modules/@types/react/index.d.ts","name":"HTMLAttributes"}],"required":false,"type":{"name":"string"}},"direction":{"defaultValue":null,"description":"The flex direction of the container. Can be row, column, row-reverse or column-reverse.","name":"direction","parent":{"fileName":"wl-hopper/packages/components/src/layout/src/Flex.tsx","name":"FlexProps"},"declarations":[{"fileName":"wl-hopper/packages/components/src/layout/src/Flex.tsx","name":"FlexProps"}],"required":false,"type":{"name":"ResponsiveProp<FlexDirection>"}},"wrap":{"defaultValue":null,"description":"Whether to wrap the flex items. The value can also be a boolean.","name":"wrap","parent":{"fileName":"wl-hopper/packages/components/src/layout/src/Flex.tsx","name":"FlexProps"},"declarations":[{"fileName":"wl-hopper/packages/components/src/layout/src/Flex.tsx","name":"FlexProps"}],"required":false,"type":{"name":"ResponsiveProp<FlexWrap> | ResponsiveProp<boolean>"}},"basis":{"defaultValue":null,"description":"An alias for the css flex-basis property.","name":"basis","parent":{"fileName":"wl-hopper/packages/components/src/layout/src/Flex.tsx","name":"FlexProps"},"declarations":[{"fileName":"wl-hopper/packages/components/src/layout/src/Flex.tsx","name":"FlexProps"}],"required":false,"type":{"name":"ResponsiveProp<FlexBasis<0 | (string & {})>>"}},"grow":{"defaultValue":null,"description":"An alias for the css flex-grow property.","name":"grow","parent":{"fileName":"wl-hopper/packages/components/src/layout/src/Flex.tsx","name":"FlexProps"},"declarations":[{"fileName":"wl-hopper/packages/components/src/layout/src/Flex.tsx","name":"FlexProps"}],"required":false,"type":{"name":"ResponsiveProp<FlexGrow>"}},"shrink":{"defaultValue":null,"description":"An alias for the css flex-shrink property.","name":"shrink","parent":{"fileName":"wl-hopper/packages/components/src/layout/src/Flex.tsx","name":"FlexProps"},"declarations":[{"fileName":"wl-hopper/packages/components/src/layout/src/Flex.tsx","name":"FlexProps"}],"required":false,"type":{"name":"ResponsiveProp<FlexShrink>"}},"inline":{"defaultValue":null,"description":"Whether to display the flex container as an inline element.","name":"inline","parent":{"fileName":"wl-hopper/packages/components/src/layout/src/Flex.tsx","name":"FlexProps"},"declarations":[{"fileName":"wl-hopper/packages/components/src/layout/src/Flex.tsx","name":"FlexProps"}],"required":false,"type":{"name":"boolean"}}},"groups":{"default":{"style":{"defaultValue":null,"description":"","name":"style","parent":{"fileName":"wl-hopper/node_modules/.pnpm/@types+react@18.3.3/node_modules/@types/react/index.d.ts","name":"HTMLAttributes"},"declarations":[{"fileName":"wl-hopper/node_modules/.pnpm/@types+react@18.3.3/node_modules/@types/react/index.d.ts","name":"HTMLAttributes"}],"required":false,"type":{"name":"CSSProperties"}},"className":{"defaultValue":null,"description":"","name":"className","parent":{"fileName":"wl-hopper/node_modules/.pnpm/@types+react@18.3.3/node_modules/@types/react/index.d.ts","name":"HTMLAttributes"},"declarations":[{"fileName":"wl-hopper/node_modules/.pnpm/@types+react@18.3.3/node_modules/@types/react/index.d.ts","name":"HTMLAttributes"}],"required":false,"type":{"name":"string"}},"id":{"defaultValue":null,"description":"","name":"id","parent":{"fileName":"wl-hopper/node_modules/.pnpm/@types+react@18.3.3/node_modules/@types/react/index.d.ts","name":"HTMLAttributes"},"declarations":[{"fileName":"wl-hopper/node_modules/.pnpm/@types+react@18.3.3/node_modules/@types/react/index.d.ts","name":"HTMLAttributes"}],"required":false,"type":{"name":"string"}},"direction":{"defaultValue":null,"description":"The flex direction of the container. Can be row, column, row-reverse or column-reverse.","name":"direction","parent":{"fileName":"wl-hopper/packages/components/src/layout/src/Flex.tsx","name":"FlexProps"},"declarations":[{"fileName":"wl-hopper/packages/components/src/layout/src/Flex.tsx","name":"FlexProps"}],"required":false,"type":{"name":"ResponsiveProp<FlexDirection>"}},"wrap":{"defaultValue":null,"description":"Whether to wrap the flex items. The value can also be a boolean.","name":"wrap","parent":{"fileName":"wl-hopper/packages/components/src/layout/src/Flex.tsx","name":"FlexProps"},"declarations":[{"fileName":"wl-hopper/packages/components/src/layout/src/Flex.tsx","name":"FlexProps"}],"required":false,"type":{"name":"ResponsiveProp<FlexWrap> | ResponsiveProp<boolean>"}},"basis":{"defaultValue":null,"description":"An alias for the css flex-basis property.","name":"basis","parent":{"fileName":"wl-hopper/packages/components/src/layout/src/Flex.tsx","name":"FlexProps"},"declarations":[{"fileName":"wl-hopper/packages/components/src/layout/src/Flex.tsx","name":"FlexProps"}],"required":false,"type":{"name":"ResponsiveProp<FlexBasis<0 | (string & {})>>"}},"grow":{"defaultValue":null,"description":"An alias for the css flex-grow property.","name":"grow","parent":{"fileName":"wl-hopper/packages/components/src/layout/src/Flex.tsx","name":"FlexProps"},"declarations":[{"fileName":"wl-hopper/packages/components/src/layout/src/Flex.tsx","name":"FlexProps"}],"required":false,"type":{"name":"ResponsiveProp<FlexGrow>"}},"shrink":{"defaultValue":null,"description":"An alias for the css flex-shrink property.","name":"shrink","parent":{"fileName":"wl-hopper/packages/components/src/layout/src/Flex.tsx","name":"FlexProps"},"declarations":[{"fileName":"wl-hopper/packages/components/src/layout/src/Flex.tsx","name":"FlexProps"}],"required":false,"type":{"name":"ResponsiveProp<FlexShrink>"}},"inline":{"defaultValue":null,"description":"Whether to display the flex container as an inline element.","name":"inline","parent":{"fileName":"wl-hopper/packages/components/src/layout/src/Flex.tsx","name":"FlexProps"},"declarations":[{"fileName":"wl-hopper/packages/components/src/layout/src/Flex.tsx","name":"FlexProps"}],"required":false,"type":{"name":"boolean"}}},"events":{},"accessibility":{},"layout":{}}}]